validictory/__init__.py
validictory/validator.py
validictory-1.1.3.dist-info/AUTHORS.txt
validictory-1.1.3.dist-info/LICENSE.txt
validictory-1.1.3.dist-info/METADATA
validictory-1.1.3.dist-info/WHEEL
validictory-1.1.3.dist-info/top_level.txt
validictory-1.1.3.dist-info/RECORD
